sentineliqsdk/__init__.py
sentineliqsdk/constants.py
sentineliqsdk/models.py
sentineliqsdk/analyzers/__init__.py
sentineliqsdk/analyzers/abuseipdb.py
sentineliqsdk/analyzers/anyrun.py
sentineliqsdk/analyzers/autofocus.py
sentineliqsdk/analyzers/axur.py
sentineliqsdk/analyzers/base.py
sentineliqsdk/analyzers/censys.py
sentineliqsdk/analyzers/circl_hashlookup.py
sentineliqsdk/analyzers/circl_passivedns.py
sentineliqsdk/analyzers/circl_passivessl.py
sentineliqsdk/analyzers/circl_vulnerability_lookup.py
sentineliqsdk/analyzers/mcap.py
sentineliqsdk/analyzers/shodan.py
sentineliqsdk/clients/__init__.py
sentineliqsdk/clients/axur.py
sentineliqsdk/clients/shodan.py
sentineliqsdk/core/__init__.py
sentineliqsdk/core/contracts.py
sentineliqsdk/core/worker.py
sentineliqsdk/core/config/__init__.py
sentineliqsdk/core/config/proxy.py
sentineliqsdk/core/config/secrets.py
sentineliqsdk/extractors/__init__.py
sentineliqsdk/extractors/detectors.py
sentineliqsdk/extractors/regex.py
sentineliqsdk/responders/__init__.py
sentineliqsdk/responders/base.py
sentineliqsdk/responders/kafka_rest.py
sentineliqsdk/responders/rabbitmq_http.py
sentineliqsdk/responders/smtp_gmail.py
sentineliqsdk/responders/smtp_outlook.py
sentineliqsdk/responders/webhook.py
sentineliqsdk-0.3.0.dist-info/METADATA
sentineliqsdk-0.3.0.dist-info/WHEEL
sentineliqsdk-0.3.0.dist-info/RECORD
