Metadata-Version: 2.4
Name: sentineliqsdk
Version: 0.3.0
Summary: A Python library of utility classes for SentinelIQ analyzers and responders
Project-URL: homepage, https://github.com/killsearch/sentineliqsdk
Project-URL: source, https://github.com/killsearch/sentineliqsdk
Project-URL: changelog, https://github.com/killsearch/sentineliqsdk/blob/main/CHANGELOG.md
Project-URL: releasenotes, https://github.com/killsearch/sentineliqsdk/releases
Project-URL: documentation, https://killsearch.github.io/sentineliqsdk/
Project-URL: issues, https://github.com/killsearch/sentineliqsdk/issues
Author-email: Sentineliq Team <team@sentineliq.com.br>
Requires-Python: <4.0,>=3.13
Requires-Dist: autofocus-client-library>=4.0.12
Requires-Dist: censys-platform>=0.8.0
Requires-Dist: httpx>=0.27.0
Requires-Dist: mkdocs-mermaid2-plugin>=1.2.2
Requires-Dist: pypdns>=2.2.8
Requires-Dist: pypssl>=2.2
Requires-Dist: pyvulnerabilitylookup>=2.14.0
Requires-Dist: pyyaml>=6.0.2
